iers/__init__.py
iers/core.py
iers/historic_dont_use.py
iers/time.py
iers-1.4.0.dist-info/LICENSE.txt
iers-1.4.0.dist-info/METADATA
iers-1.4.0.dist-info/WHEEL
iers-1.4.0.dist-info/top_level.txt
iers-1.4.0.dist-info/RECORD
