Metadata-Version: 2.1
Name: iers
Version: 1.4.0
Summary: Retrieve data from International Earth Rotation Srvice (IERS)
Home-page: https://github.com/behrouzz/iers
Author: Behrouz Safari
Author-email: behrouz.safari@gmail.com
License: MIT
Classifier: Programming Language :: Python :: 3
Classifier: License :: OSI Approved :: MIT License
Classifier: Operating System :: OS Independent
Requires-Python: >=3.6
License-File: LICENSE.txt
Requires-Dist: numpy
Requires-Dist: pandas
